chunky_mcp_utils/__init__.py
chunky_mcp_utils/chunker.py
chunky_mcp_utils-0.1.3.dist-info/METADATA
chunky_mcp_utils-0.1.3.dist-info/WHEEL
chunky_mcp_utils-0.1.3.dist-info/top_level.txt
chunky_mcp_utils-0.1.3.dist-info/RECORD
