Metadata-Version: 2.4
Name: chunky-mcp-utils
Version: 0.1.3
Summary: Utilities for handling large responses in chunky-mcp tools
Author-email: Ethan Winters <ebwinters@comcast.net>
License: MIT
Requires-Python: >=3.12
Requires-Dist: mcp[cli]>=1.9.4
